README.txt
setup.cfg
setup.py
django/__init__.py
django/bin/__init__.py
django/bin/compile-messages.py
django/bin/daily_cleanup.py
django/bin/django-admin.py
django/bin/make-messages.py
django/bin/unique-messages.py
django/bin/profiling/__init__.py
django/bin/profiling/gather_profile_stats.py
django/conf/__init__.py
django/conf/global_settings.py
django/conf/app_template/__init__.py
django/conf/app_template/models.py
django/conf/app_template/tests.py
django/conf/app_template/views.py
django/conf/project_template/__init__.py
django/conf/project_template/manage.py
django/conf/project_template/settings.py
django/conf/project_template/urls.py
django/conf/urls/__init__.py
django/conf/urls/defaults.py
django/conf/urls/i18n.py
django/conf/urls/shortcut.py
django/contrib/__init__.py
django/contrib/admin/__init__.py
django/contrib/admin/filterspecs.py
django/contrib/admin/helpers.py
django/contrib/admin/models.py
django/contrib/admin/options.py
django/contrib/admin/sites.py
django/contrib/admin/util.py
django/contrib/admin/validation.py
django/contrib/admin/widgets.py
django/contrib/admin/templatetags/__init__.py
django/contrib/admin/templatetags/admin_list.py
django/contrib/admin/templatetags/admin_modify.py
django/contrib/admin/templatetags/adminmedia.py
django/contrib/admin/templatetags/log.py
django/contrib/admin/views/__init__.py
django/contrib/admin/views/decorators.py
django/contrib/admin/views/main.py
django/contrib/admin/views/template.py
django/contrib/admindocs/__init__.py
django/contrib/admindocs/urls.py
django/contrib/admindocs/utils.py
django/contrib/admindocs/views.py
django/contrib/auth/__init__.py
django/contrib/auth/admin.py
django/contrib/auth/backends.py
django/contrib/auth/create_superuser.py
django/contrib/auth/decorators.py
django/contrib/auth/forms.py
django/contrib/auth/middleware.py
django/contrib/auth/models.py
django/contrib/auth/tokens.py
django/contrib/auth/urls.py
django/contrib/auth/views.py
django/contrib/auth/handlers/__init__.py
squash.egg-info/PKG-INFO
squash.egg-info/SOURCES.txt
squash.egg-info/dependency_links.txt
squash.egg-info/entry_points.txt
squash.egg-info/not-zip-safe
squash.egg-info/requires.txt
squash.egg-info/top_level.txt
