Metadata-Version: 1.0
Name: squash
Version: 0.5.0alpha
Summary: A distributed, highly configurable issue tracking system.
Home-page: http://www.bitbucket.org/DeadWisdom/squash/
Author: Brantley Harris
Author-email: deadwisdom@gmail.com
License: BSD
Keywords: bug tracker issue tracking project management
Platform: UNKNOWN
Classifier: Development Status :: 3 - Alpha
Classifier: Environment :: Console
Classifier: Environment :: Web Environment
Classifier: Framework :: Django
Classifier: Intended Audience :: Information Technology
Classifier: Intended Audience :: Developers
Classifier: License :: OSI Approved :: BSD License
Classifier: Topic :: Software Development :: Bug Tracking
